GenAiDataPrep/App.py
GenAiDataPrep/Config.py
GenAiDataPrep/Model.py
GenAiDataPrep/Prompt.py
GenAiDataPrep/__init__.py
genaidataprep-0.0.1.dist-info/licenses/LICENSE.md
genaidataprep-0.0.1.dist-info/METADATA
genaidataprep-0.0.1.dist-info/WHEEL
genaidataprep-0.0.1.dist-info/top_level.txt
genaidataprep-0.0.1.dist-info/RECORD
